py_structures-0.1.0.dist-info/DESCRIPTION.rst
py_structures-0.1.0.dist-info/METADATA
py_structures-0.1.0.dist-info/RECORD
py_structures-0.1.0.dist-info/WHEEL
py_structures-0.1.0.dist-info/metadata.json
py_structures-0.1.0.dist-info/top_level.txt
structures/__init__.py
structures/structures.py
tests/__init__.py
tests/unit/__init__.py
tests/unit/tests_structures.py
