Metadata-Version: 2.0
Name: py-structures
Version: 0.1.0
Summary: Pseudo C-style structs for Python
Home-page: https://github.com/bholten/structures
Author: Brennan Holten
Author-email: bholten@protonmail.ch
License: MIT
Platform: UNKNOWN
